MANIFEST.in
README.md
VERSION
setup.cfg
setup.py
bin/cmd-not-found.py
bin/cmdrec.py
bin/dnsrebind.py
bin/ip_urls.py
bin/linrshell.py
bin/php_search_vuln.py
bin/unicodes.py
bin/v0_bash_complete_msfvenom.py
bin/v0serv.py
bin/v0upload.py
bin/winrshell.py
src/v0tools/__init__.py
src/v0tools/ansi.py
src/v0tools/chars.py
src/v0tools/cli.py
src/v0tools/exceptions.py
src/v0tools/fzfhelper.py
src/v0tools/ips.py
src/v0tools/msf.py
src/v0tools/net.py
src/v0tools/syspkgs.py
src/v0tools/tests.py
src/v0tools/web.py
src/v0tools.egg-info/PKG-INFO
src/v0tools.egg-info/SOURCES.txt
src/v0tools.egg-info/dependency_links.txt
src/v0tools.egg-info/requires.txt
src/v0tools.egg-info/top_level.txt
src/v0tools/attacks/__init__.py
src/v0tools/attacks/dnsrebind.py
src/v0tools/lib/__init__.py
src/v0tools/lib/filesystem.py
src/v0tools/lib/log.py
src/v0tools/lib/util.py
src/v0tools/media/__init__.py
src/v0tools/media/convert.py
src/v0tools/media/screencast.py
src/v0tools/servers/__init__.py
src/v0tools/servers/httpserv.py
src/v0tools_doc/__init__.py
src/v0tools_doc/badges.py
src/v0tools_doc/changelog.py
src/v0tools_doc/cli.py
src/v0tools_doc/hugo.py
src/v0tools_doc/template.py