Metadata-Version: 2.1
Name: v0tools
Version: 0.0.3
Summary: This collection of tools helps navigate some of the more tedious parts of CTF'ing
Home-page: https://v0tools.stev0.me
Author: Steven Hollingsworth
Author-email: hollingsworth.stevend@gmail.com
License: MIT
Project-URL: Changes, https://v0tools.stev0.me/changelog/
Project-URL: Source Code, https://github.com/shollingsworth/v0tools
Project-URL: Issue Tracker, https://github.com/shollingsworth/v0tools/issues/
Project-URL: Twitter, https://twitter.com/_stevo
Project-URL: Documentation, https://v0tools.stev0.me
Keywords: hacking,ctf,crypto
Platform: UNKNOWN
Classifier: Development Status :: 3 - Alpha
Classifier: Environment :: Console
Classifier: License :: OSI Approved :: MIT License
Classifier: Intended Audience :: End Users/Desktop
Classifier: Intended Audience :: Information Technology
Classifier: Operating System :: POSIX :: Linux
Classifier: Programming Language :: Python :: 3 :: Only
Classifier: Programming Language :: Python :: 3.6
Classifier: Programming Language :: Python :: 3.7
Classifier: Programming Language :: Python :: 3.8
Classifier: Programming Language :: Python :: 3.9
Classifier: Topic :: Security
Classifier: Topic :: Security :: Cryptography
Requires-Python: >=3.6
